{"styles": {"pygments-hll": {"backColor": " #ffffcc"}, "pygments-sr": {"textColor": " #009999"}, "pygments-s1": {"textColor": " #aa5500"}, "pygments-mo": {"textColor": " #009999"}, "pygments-kt": {"textColor": " #00aaaa"}, "pygments-cm": {"textColor": " #aaaaaa"}, "pygments-kr": {"textColor": " #0000aa"}, "pygments-kp": {"textColor": " #0000aa"}, "pygments-mh": {"textColor": " #009999"}, "pygments-mi": {"textColor": " #009999"}, "pygments-vg": {"textColor": " #aa0000"}, "pygments-s2": {"textColor": " #aa5500"}, "pygments-ow": {"textColor": " #0000aa"}, "pygments-vc": {"textColor": " #aa0000"}, "pygments-c": {"textColor": " #aaaaaa"}, "pygments-il": {"textColor": " #009999"}, "pygments-kd": {"textColor": " #0000aa"}, "pygments-kc": {"textColor": " #0000aa"}, "pygments-kn": {"textColor": " #0000aa"}, "pygments-cs": {"textColor": " #0000aa"}, "pygments-cp": {"textColor": " #4c8317"}, "pygments-gr": {"textColor": " #aa0000"}, "pygments-gs": {}, "pygments-gp": {"textColor": " #555555"}, "pygments-gt": {"textColor": " #aa0000"}, "pygments-gu": {"textColor": " #800080"}, "pygments-w": {"textColor": " #bbbbbb"}, "pygments-s": {"textColor": " #aa5500"}, "pygments-m": {"textColor": " #009999"}, "pygments-sx": {"textColor": " #aa5500"}, "pygments-k": {"textColor": " #0000aa"}, "pygments-gd": {"textColor": " #aa0000"}, "pygments-ge": {}, "pygments-vi": {"textColor": " #aa0000"}, "pygments-gh": {"textColor": " #000080"}, "pygments-gi": {"textColor": " #00aa00"}, "pygments-go": {"textColor": " #888888"}, "pygments-nd": {"textColor": " #888888"}, "pygments-nf": {"textColor": " #00aa00"}, "pygments-na": {"textColor": " #1e90ff"}, "pygments-mf": {"textColor": " #009999"}, "pygments-nc": {"textColor": " #00aa00"}, "pygments-nb": {"textColor": " #00aaaa"}, "pygments-no": {"textColor": " #aa0000"}, "pygments-nn": {"textColor": " #00aaaa"}, "pygments-ni": {"textColor": " #800000"}, "pygments-ss": {"textColor": " #0000aa"}, "pygments-sc": {"textColor": " #aa5500"}, "pygments-nt": {"textColor": " #1e90ff"}, "pygments-nv": {"textColor": " #aa0000"}, "pygments-sh": {"textColor": " #aa5500"}, "pygments-si": {"textColor": " #aa5500"}, "pygments-bp": {"textColor": " #00aaaa"}, "pygments-sd": {"textColor": " #aa5500"}, "pygments-se": {"textColor": " #aa5500"}, "pygments-sb": {"textColor": " #aa5500"}, "pygments-err": {"textColor": " #F00000", "backColor": " #F0A0A0"}, "pygments-c1": {"textColor": " #aaaaaa"}}}
